code_tokenize/__init__.py
code_tokenize/config.py
code_tokenize/parsers.py
code_tokenize/tokenizer.py
code_tokenize/tokens.py
code_tokenize/lang/__init__.py
code_tokenize/lang/base_visitors.py
code_tokenize/lang/go/__init__.py
code_tokenize/lang/java/__init__.py
code_tokenize/lang/js/__init__.py
code_tokenize/lang/php/__init__.py
code_tokenize/lang/python/__init__.py
code_tokenize/lang/python/indent.py
code_tokenize/lang/ruby/__init__.py
code_tokenize-0.2.1.dist-info/LICENSE
code_tokenize-0.2.1.dist-info/METADATA
code_tokenize-0.2.1.dist-info/WHEEL
code_tokenize-0.2.1.dist-info/top_level.txt
code_tokenize-0.2.1.dist-info/RECORD
