Metadata-Version: 2.2
Name: code_tokenize
Version: 0.2.1
Summary: Fast program tokenization and structural analysis in Python
Home-page: https://github.com/cedricrupb/code_tokenize
Download-URL: https://github.com/cedricrupb/code_tokenize/archive/refs/tags/v0.2.1.tar.gz
Author: Cedric Richter
Author-email: Cedric Richter <cedricr.upb@gmail.com>
Maintainer-email: Cedric Richter <cedricr.upb@gmail.com>
Project-URL: Homepage, https://github.com/cedricrupb/code_tokenize
Project-URL: Bug Reports, https://github.com/cedricrupb/code_tokenize/issues
Project-URL: Source, https://github.com/cedricrupb/code_tokenize
Keywords: code,tokenization,tokenize,program,language processing
Classifier: Development Status :: 3 - Alpha
Classifier: Intended Audience :: Developers
Classifier: Topic :: Software Development :: Build Tools
Classifier: License :: OSI Approved :: MIT License
Classifier: Programming Language :: Python :: 3
Classifier: Programming Language :: Python :: 3.6
Classifier: Programming Language :: Python :: 3.7
Classifier: Programming Language :: Python :: 3.8
Classifier: Programming Language :: Python :: 3.9
Classifier: Programming Language :: Python :: 3.10
Classifier: Programming Language :: Python :: 3.11
Classifier: Programming Language :: Python :: 3.12
Classifier: Programming Language :: Python :: 3.13
Classifier: Programming Language :: Python :: 3 :: Only
Requires-Python: >=3.8
License-File: LICENSE
Requires-Dist: tree_sitter
Requires-Dist: GitPython
Requires-Dist: requests
Requires-Dist: code_ast
Dynamic: author
Dynamic: download-url
Dynamic: home-page
